invz_pack/__init__.py
invz_pack/face_aligner/__init__.py
invz_pack/face_aligner/main.py
invz_pack/face_aligner/utils.py
invz_pack/face_parser/__init__.py
invz_pack/face_parser/main.py
invz_pack/face_parser/model.py
invz_pack/face_parser/resnet.py
invz_pack/face_parser/utils/__init__.py
invz_pack/face_parser/utils/mask_utils.py
invz_pack/face_parser/utils/utils.py
invz_pack/id_extractor/__init__.py
invz_pack/id_extractor/main.py
invz_pack/id_extractor/nets.py
invz_pack/lmk_detector/__init__.py
invz_pack/lmk_detector/main.py
invz_pack/utils/__init__.py
invz_pack/utils/download.py
invz_pack/utils/input.py
invz_package-0.0.8.dist-info/LICENSE.txt
invz_package-0.0.8.dist-info/METADATA
invz_package-0.0.8.dist-info/WHEEL
invz_package-0.0.8.dist-info/top_level.txt
invz_package-0.0.8.dist-info/RECORD
